{
    "2025-03-17": {
        "Edith": [],
        "Helen(F)": [],
        "Lili": [],
        "Matthew": [
            "0930-1830"
        ],
        "Ka": [
            "7-16"
        ],
        "Kit": [
            "0930-1830"
        ],
        "Paul": [
            "15-24"
        ],
        "Helen": [
            "0930-1830"
        ],
        "Waiyee": [
            "AL"
        ],
        "Cindy": [
            "10-19"
        ],
        "Aasta": [
            "ON"
        ],
        "Carol": [
            "\u81ea\u7531\u8abf\u914d"
        ],
        "Jackie": [
            "10-19"
        ],
        "Daisy": [
            "13-22"
        ],
        "Tak": [
            "PH"
        ],
        "Caroline": [
            "15-24"
        ],
        "TUNG": [],
        "Ki": [],
        "IVY": [],
        "Colin": [],
        "Sylvia": [],
        "Sandy": [],
        "Mindy": [],
        "Candy C": [],
        "Huixin": [],
        "Noel": [],
        "lin": [],
        "Candy S": [],
        "Michelle": [],
        "Karina": [],
        "Johny": [],
        "Mokee": [],
        "sang": [],
        "xuejie": []
    },
    "2025-03-18": {
        "Edith": [],
        "Helen(F)": [],
        "Lili": [
            "7-16"
        ],
        "Matthew": [
            "15-24"
        ],
        "Ka": [
            "0930-1830"
        ],
        "Kit": [
            "15-24"
        ],
        "Paul": [
            "7-16",
            "0930-1830",
            "15-24"
        ],
        "Helen": [
            "15-24"
        ],
        "Waiyee": [
            "CL"
        ],
        "Cindy": [
            "10-19"
        ],
        "Aasta": [
            "\u81ea\u7531\u8abf\u914d"
        ],
        "Carol": [
            "10-19"
        ],
        "Jackie": [
            "10-19"
        ],
        "Daisy": [
            "13-22"
        ],
        "Tak": [
            "ON"
        ],
        "Caroline": [
            "15-24"
        ],
        "TUNG": [],
        "Ki": [],
        "IVY": [],
        "Colin": [],
        "Sylvia": [],
        "Sandy": [],
        "Mindy": [],
        "Candy C": [],
        "Huixin": [],
        "Noel": [],
        "lin": [],
        "Candy S": [],
        "Michelle": [],
        "Karina": [],
        "Johny": [],
        "Mokee": [],
        "sang": [],
        "xuejie": []
    },
    "2025-03-19": {
        "Edith": [],
        "Helen(F)": [],
        "Lili": [
            "0930-1830"
        ],
        "Matthew": [
            "7-16",
            "0930-1830",
            "15-24"
        ],
        "Ka": [
            "15-24"
        ],
        "Kit": [
            "7-16",
            "0930-1830",
            "15-24"
        ],
        "Paul": [
            "7-16"
        ],
        "Helen": [
            "7-16",
            "0930-1830",
            "15-24"
        ],
        "Waiyee": [
            "10-19"
        ],
        "Cindy": [
            "AL"
        ],
        "Aasta": [
            "10-19"
        ],
        "Carol": [
            "10-19"
        ],
        "Jackie": [
            "PH"
        ],
        "Daisy": [
            "13-22"
        ],
        "Tak": [
            "\u81ea\u7531\u8abf\u914d"
        ],
        "Caroline": [
            "15-24"
        ],
        "TUNG": [],
        "Ki": [],
        "IVY": [],
        "Colin": [],
        "Sylvia": [],
        "Sandy": [],
        "Mindy": [],
        "Candy C": [],
        "Huixin": [],
        "Noel": [],
        "lin": [],
        "Candy S": [],
        "Michelle": [],
        "Karina": [],
        "Johny": [],
        "Mokee": [],
        "sang": [],
        "xuejie": []
    },
    "2025-03-20": {
        "Edith": [],
        "Helen(F)": [],
        "Lili": [
            "15-24"
        ],
        "Matthew": [
            "7-16"
        ],
        "Ka": [
            "7-16",
            "0930-1830",
            "15-24"
        ],
        "Kit": [
            "7-16"
        ],
        "Paul": [
            "0930-1830"
        ],
        "Waiyee": [
            "10-19"
        ],
        "Cindy": [
            "CL"
        ],
        "Aasta": [
            "10-19"
        ],
        "Carol": [
            "AL"
        ],
        "Jackie": [
            "ON"
        ],
        "Daisy": [
            "CL"
        ],
        "Tak": [
            "13-22"
        ],
        "Caroline": [
            "15-24"
        ],
        "TUNG": [],
        "Ki": [],
        "IVY": [],
        "Colin": [],
        "Sylvia": [],
        "Sandy": [],
        "Mindy": [],
        "Candy C": [],
        "Huixin": [],
        "Helen": [],
        "Noel": [],
        "lin": [],
        "Candy S": [],
        "Michelle": [],
        "Karina": [],
        "Johny": [],
        "Mokee": [],
        "sang": [],
        "xuejie": []
    },
    "2025-03-21": {
        "Edith": [],
        "Helen(F)": [],
        "Lili": [],
        "Matthew": [
            "0930-1830"
        ],
        "Ka": [
            "7-16"
        ],
        "Kit": [
            "0930-1830"
        ],
        "Paul": [
            "15-24"
        ],
        "Helen": [
            "7-16"
        ],
        "Waiyee": [
            "PH"
        ],
        "Cindy": [
            "10-19"
        ],
        "Aasta": [
            "AL"
        ],
        "Carol": [
            "CL"
        ],
        "Jackie": [
            "\u81ea\u7531\u8abf\u914d"
        ],
        "Daisy": [
            "13-22"
        ],
        "Tak": [],
        "Caroline": [
            "15-24"
        ],
        "TUNG": [],
        "Ki": [],
        "IVY": [],
        "Colin": [],
        "Sylvia": [],
        "Sandy": [],
        "Mindy": [],
        "Candy C": [],
        "Huixin": [],
        "Noel": [],
        "lin": [],
        "Candy S": [],
        "Michelle": [],
        "Karina": [],
        "Johny": [],
        "Mokee": [],
        "sang": [],
        "xuejie": []
    },
    "2025-03-22": {
        "Edith": [],
        "Helen(F)": [],
        "Lili": [],
        "Matthew": [
            "15-24"
        ],
        "Ka": [
            "10-17"
        ],
        "Kit": [
            "15-24"
        ],
        "Paul": [
            "7-16",
            "10-19",
            "15-24"
        ],
        "Helen": [
            "10-17"
        ],
        "Waiyee": [
            "ON"
        ],
        "Cindy": [
            "10-19"
        ],
        "Aasta": [
            "CL"
        ],
        "Carol": [
            "10-19"
        ],
        "Jackie": [
            "10-19"
        ],
        "Daisy": [
            "13-22"
        ],
        "Tak": [
            "AL"
        ],
        "Caroline": [
            "15-24"
        ],
        "TUNG": [],
        "Ki": [],
        "IVY": [],
        "Colin": [],
        "Sylvia": [],
        "Sandy": [],
        "Mindy": [],
        "Candy C": [],
        "Huixin": [],
        "Noel": [],
        "lin": [],
        "Candy S": [],
        "Michelle": [],
        "Karina": [],
        "Johny": [],
        "Mokee": [],
        "sang": [],
        "xuejie": []
    },
    "2025-03-23": {
        "Edith": [],
        "Helen(F)": [],
        "Lili": [
            "7-16",
            "10-19",
            "15-24"
        ],
        "Matthew": [
            "7-16",
            "10-19",
            "15-24"
        ],
        "Ka": [
            "15-24"
        ],
        "Kit": [
            "7-16",
            "10-19",
            "15-24"
        ],
        "Paul": [
            "7-16"
        ],
        "Waiyee": [
            "\u81ea\u7531\u8abf\u914d"
        ],
        "Cindy": [
            "PH"
        ],
        "Aasta": [
            "10-19"
        ],
        "Carol": [
            "10-19"
        ],
        "Jackie": [
            "10-19"
        ],
        "Daisy": [
            "PH"
        ],
        "Tak": [
            "CL"
        ],
        "Caroline": [
            "15-24"
        ],
        "TUNG": [],
        "Ki": [],
        "IVY": [],
        "Colin": [],
        "Sylvia": [],
        "Sandy": [],
        "Mindy": [],
        "Candy C": [],
        "Huixin": [],
        "Helen": [],
        "Noel": [],
        "lin": [],
        "Candy S": [],
        "Michelle": [],
        "Karina": [],
        "Johny": [],
        "Mokee": [],
        "sang": [],
        "xuejie": []
    },
    "2025-03-24": {
        "Edith": [],
        "Helen(F)": [],
        "Lili": [
            "7-16"
        ],
        "Matthew": [
            "7-16"
        ],
        "Ka": [
            "7-16",
            "0930-1830",
            "15-24"
        ],
        "Kit": [
            "7-16"
        ],
        "Paul": [
            "0930-1830"
        ],
        "Helen": [
            "7-16"
        ],
        "Waiyee": [
            "10-19"
        ],
        "Cindy": [
            "ON"
        ],
        "Aasta": [
            "10-19"
        ],
        "Carol": [
            "PH"
        ],
        "Jackie": [
            "AL"
        ],
        "Daisy": [
            "ON"
        ],
        "Tak": [
            "13-22"
        ],
        "Caroline": [
            "15-24"
        ],
        "TUNG": [],
        "Ki": [],
        "IVY": [],
        "Colin": [],
        "Sylvia": [],
        "Sandy": [],
        "Mindy": [],
        "Candy C": [],
        "Huixin": [],
        "Noel": [],
        "lin": [],
        "Candy S": [],
        "Michelle": [],
        "Karina": [],
        "Johny": [],
        "Mokee": [],
        "sang": [],
        "xuejie": []
    },
    "2025-03-25": {
        "Edith": [],
        "Helen(F)": [],
        "Lili": [
            "0930-1830"
        ],
        "Matthew": [
            "0930-1830"
        ],
        "Ka": [
            "7-16"
        ],
        "Kit": [
            "0930-1830"
        ],
        "Paul": [
            "15-24"
        ],
        "Helen": [
            "0930-1830"
        ],
        "Waiyee": [
            "10-19"
        ],
        "Cindy": [
            "\u81ea\u7531\u8abf\u914d"
        ],
        "Aasta": [
            "PH"
        ],
        "Carol": [
            "ON"
        ],
        "Jackie": [
            "CL"
        ],
        "Daisy": [
            "\u81ea\u7531\u8abf\u914d"
        ],
        "Tak": [
            "13-22"
        ],
        "Caroline": [
            "15-24"
        ],
        "TUNG": [],
        "Ki": [],
        "IVY": [],
        "Colin": [],
        "Sylvia": [],
        "Sandy": [],
        "Mindy": [],
        "Candy C": [],
        "Huixin": [],
        "Noel": [],
        "lin": [],
        "Candy S": [],
        "Michelle": [],
        "Karina": [],
        "Johny": [],
        "Mokee": [],
        "sang": [],
        "xuejie": []
    },
    "2025-03-26": {
        "Edith": [],
        "Helen(F)": [],
        "Lili": [
            "15-24"
        ],
        "Matthew": [
            "15-24"
        ],
        "Ka": [
            "0930-1830"
        ],
        "Kit": [
            "15-24"
        ],
        "Paul": [
            "7-16",
            "0930-1830",
            "15-24"
        ],
        "Helen": [
            "15-24"
        ],
        "Waiyee": [
            "AL"
        ],
        "Cindy": [
            "10-19"
        ],
        "Aasta": [
            "ON"
        ],
        "Carol": [
            "\u81ea\u7531\u8abf\u914d"
        ],
        "Jackie": [
            "10-19"
        ],
        "Daisy": [
            "13-22"
        ],
        "Tak": [
            "PH"
        ],
        "Caroline": [
            "15-24"
        ],
        "TUNG": [],
        "Ki": [],
        "IVY": [],
        "Colin": [],
        "Sylvia": [],
        "Sandy": [],
        "Mindy": [],
        "Candy C": [],
        "Huixin": [],
        "Noel": [],
        "lin": [],
        "Candy S": [],
        "Michelle": [],
        "Karina": [],
        "Johny": [],
        "Mokee": [],
        "sang": [],
        "xuejie": []
    },
    "2025-03-27": {
        "Edith": [],
        "Helen(F)": [],
        "Lili": [
            "7-16",
            "0930-1830",
            "15-24"
        ],
        "Matthew": [],
        "Ka": [
            "15-24"
        ],
        "Kit": [
            "7-16",
            "0930-1830",
            "15-24"
        ],
        "Paul": [
            "7-16"
        ],
        "Helen": [
            "7-16",
            "0930-1830",
            "15-24"
        ],
        "Waiyee": [
            "CL"
        ],
        "Cindy": [
            "10-19"
        ],
        "Aasta": [
            "\u81ea\u7531\u8abf\u914d"
        ],
        "Carol": [
            "10-19"
        ],
        "Jackie": [
            "10-19"
        ],
        "Daisy": [
            "13-22"
        ],
        "Tak": [
            "ON"
        ],
        "Caroline": [
            "15-24"
        ],
        "TUNG": [],
        "Ki": [],
        "IVY": [],
        "Colin": [],
        "Sylvia": [],
        "Sandy": [],
        "Mindy": [],
        "Candy C": [],
        "Huixin": [],
        "Noel": [],
        "lin": [],
        "Candy S": [],
        "Michelle": [],
        "Karina": [],
        "Johny": [],
        "Mokee": [],
        "sang": [],
        "xuejie": []
    },
    "2025-03-28": {
        "Edith": [],
        "Helen(F)": [],
        "Lili": [
            "7-16"
        ],
        "Matthew": [
            "7-16"
        ],
        "Ka": [
            "7-16",
            "0930-1830",
            "15-24"
        ],
        "Kit": [
            "7-16"
        ],
        "Paul": [
            "0930-1830"
        ],
        "Waiyee": [
            "10-19"
        ],
        "Cindy": [
            "AL"
        ],
        "Aasta": [
            "10-19"
        ],
        "Carol": [
            "10-19"
        ],
        "Jackie": [
            "PH"
        ],
        "Daisy": [
            "AL"
        ],
        "Tak": [
            "\u81ea\u7531\u8abf\u914d"
        ],
        "Caroline": [
            "15-24"
        ],
        "TUNG": [],
        "Ki": [],
        "IVY": [],
        "Colin": [],
        "Sylvia": [],
        "Sandy": [],
        "Mindy": [],
        "Candy C": [],
        "Huixin": [],
        "Helen": [],
        "Noel": [],
        "lin": [],
        "Candy S": [],
        "Michelle": [],
        "Karina": [],
        "Johny": [],
        "Mokee": [],
        "sang": [],
        "xuejie": []
    },
    "2025-03-29": {
        "Edith": [],
        "Helen(F)": [],
        "Lili": [
            "10-17"
        ],
        "Matthew": [
            "10-17"
        ],
        "Ka": [
            "7-16"
        ],
        "Kit": [
            "10-17"
        ],
        "Paul": [
            "15-24"
        ],
        "Helen": [
            "7-16"
        ],
        "Waiyee": [
            "10-19"
        ],
        "Cindy": [
            "CL"
        ],
        "Aasta": [
            "10-19"
        ],
        "Carol": [
            "AL"
        ],
        "Jackie": [
            "ON"
        ],
        "Daisy": [
            "CL"
        ],
        "Tak": [
            "13-22"
        ],
        "Caroline": [
            "15-24"
        ],
        "TUNG": [],
        "Ki": [],
        "IVY": [],
        "Colin": [],
        "Sylvia": [],
        "Sandy": [],
        "Mindy": [],
        "Candy C": [],
        "Huixin": [],
        "Noel": [],
        "lin": [],
        "Candy S": [],
        "Michelle": [],
        "Karina": [],
        "Johny": [],
        "Mokee": [],
        "sang": [],
        "xuejie": []
    },
    "2025-03-30": {
        "Edith": [],
        "Helen(F)": [],
        "Lili": [
            "15-24"
        ],
        "Matthew": [
            "15-24"
        ],
        "Ka": [
            "10-17"
        ],
        "Kit": [
            "15-24"
        ],
        "Paul": [
            "7-16",
            "10-19",
            "15-24"
        ],
        "Helen": [
            "10-17"
        ],
        "Waiyee": [
            "PH"
        ],
        "Cindy": [
            "10-19"
        ],
        "Aasta": [
            "AL"
        ],
        "Carol": [
            "CL"
        ],
        "Jackie": [
            "\u81ea\u7531\u8abf\u914d"
        ],
        "Daisy": [
            "13-22"
        ],
        "Tak": [
            "13-22"
        ],
        "Caroline": [
            "15-24"
        ],
        "TUNG": [],
        "Ki": [],
        "IVY": [],
        "Colin": [],
        "Sylvia": [],
        "Sandy": [],
        "Mindy": [],
        "Candy C": [],
        "Huixin": [],
        "Noel": [],
        "lin": [],
        "Candy S": [],
        "Michelle": [],
        "Karina": [],
        "Johny": [],
        "Mokee": [],
        "sang": [],
        "xuejie": []
    },
    "2025-03-31": {
        "Edith": [],
        "Helen(F)": [],
        "Lili": [
            "7-16",
            "0930-1830",
            "15-24"
        ],
        "Matthew": [
            "7-16",
            "0930-1830",
            "15-24"
        ],
        "Ka": [
            "15-24"
        ],
        "Kit": [
            "7-16",
            "0930-1830",
            "15-24"
        ],
        "Paul": [
            "7-16"
        ],
        "Helen": [
            "15-24"
        ],
        "Waiyee": [
            "ON"
        ],
        "Cindy": [
            "10-19"
        ],
        "Aasta": [
            "CL"
        ],
        "Carol": [
            "10-19"
        ],
        "Jackie": [
            "10-19"
        ],
        "Daisy": [
            "13-22"
        ],
        "Tak": [
            "AL"
        ],
        "Caroline": [
            "15-24"
        ],
        "TUNG": [],
        "Ki": [],
        "IVY": [],
        "Colin": [],
        "Sylvia": [],
        "Sandy": [],
        "Mindy": [],
        "Candy C": [],
        "Huixin": [],
        "Noel": [],
        "lin": [],
        "Candy S": [],
        "Michelle": [],
        "Karina": [],
        "Johny": [],
        "Mokee": [],
        "sang": [],
        "xuejie": []
    },
    "2025-04-01": {
        "Edith": [],
        "Helen(F)": [],
        "Lili": [
            "7-16"
        ],
        "Matthew": [
            "7-16"
        ],
        "Ka": [
            "7-16",
            "0930-1830",
            "15-24"
        ],
        "Kit": [
            "7-16"
        ],
        "Paul": [
            "0930-1830"
        ],
        "Helen": [
            "7-16",
            "0930-1830",
            "15-24"
        ],
        "Waiyee": [
            "\u81ea\u7531\u8abf\u914d"
        ],
        "Cindy": [
            "PH"
        ],
        "Aasta": [
            "10-19"
        ],
        "Carol": [
            "10-19"
        ],
        "Jackie": [
            "10-19"
        ],
        "Daisy": [
            "PH"
        ],
        "Tak": [
            "CL"
        ],
        "Caroline": [
            "15-24"
        ],
        "TUNG": [],
        "Ki": [],
        "IVY": [],
        "Colin": [],
        "Sylvia": [],
        "Sandy": [],
        "Mindy": [],
        "Candy C": [],
        "Huixin": [],
        "Noel": [],
        "lin": [],
        "Candy S": [],
        "Michelle": [],
        "Karina": [],
        "Johny": [],
        "Mokee": [],
        "sang": [],
        "xuejie": []
    },
    "2025-04-02": {
        "Edith": [],
        "Helen(F)": [],
        "Lili": [
            "0930-1830"
        ],
        "Matthew": [
            "0930-1830"
        ],
        "Ka": [
            "7-16"
        ],
        "Kit": [
            "0930-1830"
        ],
        "Paul": [
            "15-24"
        ],
        "Waiyee": [
            "10-19"
        ],
        "Cindy": [
            "ON"
        ],
        "Aasta": [
            "10-19"
        ],
        "Carol": [
            "PH"
        ],
        "Jackie": [
            "AL"
        ],
        "Daisy": [
            "ON"
        ],
        "Tak": [
            "13-22"
        ],
        "Caroline": [
            "15-24"
        ],
        "TUNG": [],
        "Ki": [],
        "IVY": [],
        "Colin": [],
        "Sylvia": [],
        "Sandy": [],
        "Mindy": [],
        "Candy C": [],
        "Huixin": [],
        "Helen": [],
        "Noel": [],
        "lin": [],
        "Candy S": [],
        "Michelle": [],
        "Karina": [],
        "Johny": [],
        "Mokee": [],
        "sang": [],
        "xuejie": []
    },
    "2025-04-03": {
        "Edith": [],
        "Helen(F)": [],
        "Lili": [
            "15-24"
        ],
        "Matthew": [
            "15-24"
        ],
        "Ka": [
            "0930-1830"
        ],
        "Kit": [
            "15-24"
        ],
        "Paul": [
            "7-16",
            "0930-1830",
            "15-24"
        ],
        "Helen": [
            "7-16"
        ],
        "Waiyee": [
            "10-19"
        ],
        "Cindy": [
            "\u81ea\u7531\u8abf\u914d"
        ],
        "Aasta": [
            "PH"
        ],
        "Carol": [
            "ON"
        ],
        "Jackie": [
            "CL"
        ],
        "Daisy": [
            "\u81ea\u7531\u8abf\u914d"
        ],
        "Tak": [
            "13-22"
        ],
        "Caroline": [
            "15-24"
        ],
        "TUNG": [],
        "Ki": [],
        "IVY": [],
        "Colin": [],
        "Sylvia": [],
        "Sandy": [],
        "Mindy": [],
        "Candy C": [],
        "Huixin": [],
        "Noel": [],
        "lin": [],
        "Candy S": [],
        "Michelle": [],
        "Karina": [],
        "Johny": [],
        "Mokee": [],
        "sang": [],
        "xuejie": []
    },
    "2025-04-04": {
        "Edith": [],
        "Helen(F)": [],
        "Lili": [
            "7-16",
            "0930-1830",
            "15-24"
        ],
        "Matthew": [
            "7-16",
            "0930-1830",
            "15-24"
        ],
        "Ka": [
            "15-24"
        ],
        "Kit": [
            "7-16",
            "0930-1830",
            "15-24"
        ],
        "Paul": [
            "7-16"
        ],
        "Helen": [
            "0930-1830"
        ],
        "Waiyee": [
            "AL"
        ],
        "Cindy": [
            "10-19"
        ],
        "Aasta": [
            "ON"
        ],
        "Carol": [
            "\u81ea\u7531\u8abf\u914d"
        ],
        "Jackie": [
            "10-19"
        ],
        "Daisy": [
            "13-22"
        ],
        "Tak": [
            "PH"
        ],
        "Caroline": [
            "15-24"
        ],
        "TUNG": [],
        "Ki": [],
        "IVY": [],
        "Colin": [],
        "Sylvia": [],
        "Sandy": [],
        "Mindy": [],
        "Candy C": [],
        "Huixin": [],
        "Noel": [],
        "lin": [],
        "Candy S": [],
        "Michelle": [],
        "Karina": [],
        "Johny": [],
        "Mokee": [],
        "sang": [],
        "xuejie": []
    },
    "2025-04-05": {
        "Edith": [],
        "Helen(F)": [],
        "Lili": [
            "7-16"
        ],
        "Matthew": [
            "7-16"
        ],
        "Ka": [
            "7-16",
            "10-19",
            "15-24"
        ],
        "Kit": [
            "7-16"
        ],
        "Paul": [
            "10-17"
        ],
        "Helen": [
            "15-24"
        ],
        "Waiyee": [
            "CL"
        ],
        "Cindy": [
            "10-19"
        ],
        "Aasta": [
            "\u81ea\u7531\u8abf\u914d"
        ],
        "Carol": [
            "10-19"
        ],
        "Jackie": [
            "10-19"
        ],
        "Daisy": [
            "13-22"
        ],
        "Tak": [
            "ON"
        ],
        "Caroline": [
            "15-24"
        ],
        "TUNG": [],
        "Ki": [],
        "IVY": [],
        "Colin": [],
        "Sylvia": [],
        "Sandy": [],
        "Mindy": [],
        "Candy C": [],
        "Huixin": [],
        "Noel": [],
        "lin": [],
        "Candy S": [],
        "Michelle": [],
        "Karina": [],
        "Johny": [],
        "Mokee": [],
        "sang": [],
        "xuejie": []
    },
    "2025-04-06": {
        "Edith": [],
        "Helen(F)": [],
        "Lili": [
            "10-17"
        ],
        "Matthew": [
            "10-17"
        ],
        "Ka": [
            "7-16"
        ],
        "Kit": [
            "10-17"
        ],
        "Paul": [
            "15-24"
        ],
        "Helen": [
            "7-16",
            "10-19",
            "15-24"
        ],
        "Waiyee": [
            "10-19"
        ],
        "Cindy": [
            "AL"
        ],
        "Aasta": [
            "10-19"
        ],
        "Carol": [
            "10-19"
        ],
        "Jackie": [
            "PH"
        ],
        "Daisy": [
            "AL"
        ],
        "Tak": [
            "\u81ea\u7531\u8abf\u914d"
        ],
        "Caroline": [
            "15-24"
        ],
        "TUNG": [],
        "Ki": [],
        "IVY": [],
        "Colin": [],
        "Sylvia": [],
        "Sandy": [],
        "Mindy": [],
        "Candy C": [],
        "Huixin": [],
        "Noel": [],
        "lin": [],
        "Candy S": [],
        "Michelle": [],
        "Karina": [],
        "Johny": [],
        "Mokee": [],
        "sang": [],
        "xuejie": []
    },
    "2025-04-07": {
        "Edith": [],
        "Helen(F)": [],
        "Lili": [
            "15-24"
        ],
        "Matthew": [
            "15-24"
        ],
        "Ka": [
            "0930-1830"
        ],
        "Kit": [
            "15-24"
        ],
        "Paul": [
            "7-16",
            "0930-1830",
            "15-24"
        ],
        "Waiyee": [
            "10-19"
        ],
        "Cindy": [
            "CL"
        ],
        "Aasta": [
            "10-19"
        ],
        "Carol": [
            "AL"
        ],
        "Jackie": [
            "ON"
        ],
        "Daisy": [
            "CL"
        ],
        "Tak": [
            "13-22"
        ],
        "Caroline": [
            "15-24"
        ],
        "TUNG": [],
        "Ki": [],
        "IVY": [],
        "Colin": [],
        "Sylvia": [],
        "Sandy": [],
        "Mindy": [],
        "Candy C": [],
        "Huixin": [],
        "Helen": [],
        "Noel": [],
        "lin": [],
        "Candy S": [],
        "Michelle": [],
        "Karina": [],
        "Johny": [],
        "Mokee": [],
        "sang": [],
        "xuejie": []
    },
    "2025-04-08": {
        "Edith": [],
        "Helen(F)": [],
        "Lili": [
            "7-16",
            "0930-1830",
            "15-24"
        ],
        "Matthew": [
            "7-16",
            "0930-1830",
            "15-24"
        ],
        "Ka": [
            "15-24"
        ],
        "Kit": [
            "7-16",
            "0930-1830",
            "15-24"
        ],
        "Paul": [
            "7-16"
        ],
        "Helen": [
            "7-16"
        ],
        "Waiyee": [
            "PH"
        ],
        "Cindy": [
            "10-19"
        ],
        "Aasta": [
            "AL"
        ],
        "Carol": [
            "CL"
        ],
        "Jackie": [
            "\u81ea\u7531\u8abf\u914d"
        ],
        "Daisy": [
            "13-22"
        ],
        "Tak": [
            "13-22"
        ],
        "Caroline": [
            "15-24"
        ],
        "TUNG": [],
        "Ki": [],
        "IVY": [],
        "Colin": [],
        "Sylvia": [],
        "Sandy": [],
        "Mindy": [],
        "Candy C": [],
        "Huixin": [],
        "Noel": [],
        "lin": [],
        "Candy S": [],
        "Michelle": [],
        "Karina": [],
        "Johny": [],
        "Mokee": [],
        "sang": [],
        "xuejie": []
    },
    "2025-04-09": {
        "Edith": [],
        "Helen(F)": [],
        "Lili": [
            "7-16"
        ],
        "Matthew": [
            "7-16"
        ],
        "Ka": [
            "7-16",
            "0930-1830",
            "15-24"
        ],
        "Kit": [
            "7-16"
        ],
        "Paul": [
            "0930-1830"
        ],
        "Helen": [
            "0930-1830"
        ],
        "Waiyee": [
            "ON"
        ],
        "Cindy": [
            "10-19"
        ],
        "Aasta": [
            "CL"
        ],
        "Carol": [
            "10-19"
        ],
        "Jackie": [
            "10-19"
        ],
        "Daisy": [
            "13-22"
        ],
        "Tak": [
            "AL"
        ],
        "Caroline": [
            "15-24"
        ],
        "TUNG": [],
        "Ki": [],
        "IVY": [],
        "Colin": [],
        "Sylvia": [],
        "Sandy": [],
        "Mindy": [],
        "Candy C": [],
        "Huixin": [],
        "Noel": [],
        "lin": [],
        "Candy S": [],
        "Michelle": [],
        "Karina": [],
        "Johny": [],
        "Mokee": [],
        "sang": [],
        "xuejie": []
    },
    "2025-04-10": {
        "Edith": [],
        "Helen(F)": [],
        "Lili": [
            "0930-1830"
        ],
        "Matthew": [
            "0930-1830"
        ],
        "Ka": [
            "7-16"
        ],
        "Kit": [
            "0930-1830"
        ],
        "Paul": [
            "15-24"
        ],
        "Helen": [
            "15-24"
        ],
        "Waiyee": [
            "\u81ea\u7531\u8abf\u914d"
        ],
        "Cindy": [
            "PH"
        ],
        "Aasta": [
            "10-19"
        ],
        "Carol": [
            "10-19"
        ],
        "Jackie": [
            "10-19"
        ],
        "Tak": [
            "CL"
        ],
        "Daisy": [
            "13-22"
        ],
        "Caroline": [
            "15-24"
        ],
        "TUNG": [],
        "Ki": [],
        "IVY": [],
        "Colin": [],
        "Sylvia": [],
        "Sandy": [],
        "Mindy": [],
        "Candy C": [],
        "Huixin": [],
        "Noel": [],
        "lin": [],
        "Candy S": [],
        "Michelle": [],
        "Karina": [],
        "Johny": [],
        "Mokee": [],
        "sang": [],
        "xuejie": []
    },
    "2025-04-11": {
        "Edith": [],
        "Helen(F)": [],
        "Lili": [
            "15-24"
        ],
        "Matthew": [
            "15-24"
        ],
        "Ka": [
            "0930-1830"
        ],
        "Kit": [
            "15-24"
        ],
        "Paul": [
            "7-16",
            "0930-1830",
            "15-24"
        ],
        "Helen": [
            "7-16",
            "0930-1830",
            "15-24"
        ],
        "Waiyee": [
            "10-19"
        ],
        "Cindy": [
            "ON"
        ],
        "Aasta": [
            "10-19"
        ],
        "Carol": [
            "PH"
        ],
        "Jackie": [
            "AL"
        ],
        "Daisy": [
            "ON"
        ],
        "Tak": [
            "13-22"
        ],
        "Caroline": [
            "15-24"
        ],
        "TUNG": [],
        "Ki": [],
        "IVY": [],
        "Colin": [],
        "Sylvia": [],
        "Sandy": [],
        "Mindy": [],
        "Candy C": [],
        "Huixin": [],
        "Noel": [],
        "lin": [],
        "Candy S": [],
        "Michelle": [],
        "Karina": [],
        "Johny": [],
        "Mokee": [],
        "sang": [],
        "xuejie": []
    },
    "2025-04-12": {
        "Edith": [],
        "Helen(F)": [],
        "Lili": [
            "7-16",
            "10-19",
            "15-24"
        ],
        "Matthew": [
            "7-16",
            "10-19",
            "15-24"
        ],
        "Ka": [],
        "Kit": [],
        "Paul": [],
        "Waiyee": [
            "10-19"
        ],
        "Cindy": [
            "\u81ea\u7531\u8abf\u914d"
        ],
        "Aasta": [
            "PH"
        ],
        "Carol": [
            "ON"
        ],
        "Jackie": [
            "CL"
        ],
        "Daisy": [
            "\u81ea\u7531\u8abf\u914d"
        ],
        "Tak": [
            "13-22"
        ],
        "Caroline": [
            "15-24"
        ],
        "TUNG": [],
        "Ki": [],
        "IVY": [],
        "Colin": [],
        "Sylvia": [],
        "Sandy": [],
        "Mindy": [],
        "Candy C": [],
        "Huixin": [],
        "Helen": [],
        "Noel": [],
        "lin": [],
        "Candy S": [],
        "Michelle": [],
        "Karina": [],
        "Johny": [],
        "Mokee": [],
        "sang": [],
        "xuejie": []
    },
    "2025-04-13": {
        "Edith": [],
        "Helen(F)": [],
        "Lili": [
            "7-16"
        ],
        "Matthew": [],
        "Ka": [],
        "Kit": [],
        "Paul": [],
        "Helen": [
            "7-16"
        ],
        "Waiyee": [
            "AL"
        ],
        "Cindy": [
            "10-19"
        ],
        "Aasta": [
            "ON"
        ],
        "Carol": [
            "\u81ea\u7531\u8abf\u914d"
        ],
        "Jackie": [
            "10-19"
        ],
        "Daisy": [
            "13-22"
        ],
        "Tak": [
            "PH"
        ],
        "Caroline": [
            "15-24"
        ],
        "TUNG": [],
        "Ki": [],
        "IVY": [],
        "Colin": [],
        "Sylvia": [],
        "Sandy": [],
        "Mindy": [],
        "Candy C": [],
        "Huixin": [],
        "Noel": [],
        "lin": [],
        "Candy S": [],
        "Michelle": [],
        "Karina": [],
        "Johny": [],
        "Mokee": [],
        "sang": [],
        "xuejie": []
    },
    "2025-04-14": {
        "Edith": [],
        "Helen(F)": [],
        "Lili": [],
        "Matthew": [],
        "Ka": [],
        "Kit": [],
        "Paul": [],
        "Helen": [
            "0930-1830"
        ],
        "Waiyee": [
            "CL"
        ],
        "Cindy": [
            "10-19"
        ],
        "Aasta": [
            "\u81ea\u7531\u8abf\u914d"
        ],
        "Carol": [
            "10-19"
        ],
        "Jackie": [
            "10-19"
        ],
        "Daisy": [
            "13-22"
        ],
        "Tak": [
            "ON"
        ],
        "Caroline": [
            "15-24"
        ],
        "TUNG": [],
        "Ki": [],
        "IVY": [],
        "Colin": [],
        "Sylvia": [],
        "Sandy": [],
        "Mindy": [],
        "Candy C": [],
        "Huixin": [],
        "Noel": [],
        "lin": [],
        "Candy S": [],
        "Michelle": [],
        "Karina": [],
        "Johny": [],
        "Mokee": [],
        "sang": [],
        "xuejie": []
    },
    "2025-04-17": {
        "Edith": [],
        "Helen(F)": [],
        "Lili": [],
        "Matthew": [],
        "Ka": [],
        "Kit": [],
        "Paul": [],
        "Waiyee": [
            "10-19"
        ],
        "Cindy": [
            "AL"
        ],
        "Aasta": [
            "10-19"
        ],
        "Carol": [
            "10-19"
        ],
        "Jackie": [
            "PH"
        ],
        "Daisy": [
            "AL"
        ],
        "Tak": [
            "\u81ea\u7531\u8abf\u914d"
        ],
        "Caroline": [
            "15-24"
        ],
        "TUNG": [],
        "Ki": [],
        "IVY": [],
        "Colin": [],
        "Sylvia": [],
        "Sandy": [],
        "Mindy": [],
        "Candy C": [],
        "Huixin": [],
        "Helen": [],
        "Noel": [],
        "lin": [],
        "Candy S": [],
        "Michelle": [],
        "Karina": [],
        "Johny": [],
        "Mokee": [],
        "sang": [],
        "xuejie": []
    },
    "2025-03-16": {
        "TUNG": [],
        "Daisy": [],
        "Tak": [],
        "Ki": [],
        "IVY": [],
        "Colin": [],
        "Sylvia": [],
        "Caroline": [],
        "Waiyee": [],
        "Aasta": [],
        "Carol": [],
        "Cindy": [],
        "Sandy": [],
        "Mindy": [],
        "Jackie": [],
        "Candy C": [],
        "Huixin": [],
        "Helen": [],
        "Noel": [],
        "lin": [],
        "Candy S": [],
        "Michelle": [],
        "Karina": [],
        "Johny": [],
        "Edith": [],
        "Helen(F)": [],
        "Lili": [],
        "Matthew": [],
        "Ka": [],
        "Kit": [],
        "Paul": [],
        "Mokee": [],
        "sang": [],
        "xuejie": []
    }
}